pyThorlabsPM100A/__init__.py
pyThorlabsPM100A/driver.py
pyThorlabsPM100A/main.py
pyThorlabsPM100A/plots.py
pyThorlabsPM100A/settings.ini
pyThorlabsPM100A/graphics/pause.png
pyThorlabsPM100A/graphics/play.png
pyThorlabsPM100A/graphics/refresh.png
pyThorlabsPM100A/graphics/stop.png
pyThorlabsPM100A-0.7.dist-info/METADATA
pyThorlabsPM100A-0.7.dist-info/WHEEL
pyThorlabsPM100A-0.7.dist-info/entry_points.txt
pyThorlabsPM100A-0.7.dist-info/top_level.txt
pyThorlabsPM100A-0.7.dist-info/RECORD
