Metadata-Version: 2.1
Name: pyThorlabsPM100A
Version: 0.7
Summary: A python library/GUI to access and control the PM100A powermeter of Thorlabs.
Home-page: https://github.com/MicheleCotrufo/
Author: Michele Cotrufo
Author-email: michele.cotrufo@gmail.com
License: MIT
Platform: UNKNOWN
Requires-Dist: PyQt5 (>=5.15.6)
Requires-Dist: pyqtgraph
Requires-Dist: pyvisa
Requires-Dist: numpy
